[
  {
    "description": "    As the user, I want to search and order an InsolvencyNZ",
    "keyword": "Feature",
    "name": "InsolvencyNZ Order",
    "line": 1,
    "id": "insolvencynz-order",
    "tags": [],
    "uri": "Convencing_InsolvencyNZ.feature",
    "elements": [
      {
        "id": "insolvencynz-order;validation-the-user-can-search-and-order-by-name",
        "keyword": "Scenario",
        "line": 8,
        "name": "Validation the user can search and order by Name",
        "tags": [],
        "type": "scenario",
        "steps": [
          {
            "arguments": [],
            "keyword": "Given ",
            "line": 5,
            "name": "the user logins to InsolvencyNZ search page",
            "result": {
              "status": "passed",
              "duration": 11942000000
            }
          },
          {
            "arguments": [],
            "keyword": "When ",
            "line": 9,
            "name": "the user inputs Mater value and Search By Name",
            "result": {
              "status": "passed",
              "duration": 6637000000
            }
          },
          {
            "arguments": [],
            "keyword": "Then ",
            "line": 10,
            "name": "the user see the list of InsolvencyNZ related to Name display",
            "result": {
              "status": "passed",
              "duration": 375000000
            }
          },
          {
            "arguments": [],
            "keyword": "And ",
            "line": 11,
            "name": "the the user selects a Document related with name to Order",
            "result": {
              "status": "passed",
              "duration": 6299000000
            }
          },
          {
            "arguments": [],
            "keyword": "Then ",
            "line": 12,
            "name": "the user sees the Order related to Name created successfully",
            "result": {
              "status": "passed",
              "duration": 416000000
            }
          }
        ]
      },
      {
        "id": "insolvencynz-order;validation-the-user-can-search-and-order-by-documentid",
        "keyword": "Scenario",
        "line": 15,
        "name": "Validation the user can search and order by DocumentID",
        "tags": [],
        "type": "scenario",
        "steps": [
          {
            "arguments": [],
            "keyword": "Given ",
            "line": 5,
            "name": "the user logins to InsolvencyNZ search page",
            "result": {
              "status": "passed",
              "duration": 7820000000
            }
          },
          {
            "arguments": [],
            "keyword": "When ",
            "line": 16,
            "name": "the user inputs Mater value and Search By DocumentID",
            "result": {
              "status": "passed",
              "duration": 6821000000
            }
          },
          {
            "arguments": [],
            "keyword": "Then ",
            "line": 17,
            "name": "the user sees the document ID is generated successfully",
            "result": {
              "status": "passed",
              "duration": 348000000
            }
          },
          {
            "arguments": [],
            "keyword": "And ",
            "line": 18,
            "name": "the user clicks on Order to order with this DocumentID",
            "result": {
              "status": "passed",
              "duration": 6346000000
            }
          },
          {
            "arguments": [],
            "keyword": "Then ",
            "line": 19,
            "name": "the user sees the Order related to DocumentID created successfully",
            "result": {
              "status": "passed",
              "duration": 359000000
            }
          }
        ]
      },
      {
        "id": "insolvencynz-order;validation-the-user-can-search-and-order-by-document-status",
        "keyword": "Scenario",
        "line": 22,
        "name": "Validation the user can search and order by Document status",
        "tags": [],
        "type": "scenario",
        "steps": [
          {
            "arguments": [],
            "keyword": "Given ",
            "line": 5,
            "name": "the user logins to InsolvencyNZ search page",
            "result": {
              "status": "passed",
              "duration": 7232000000
            }
          },
          {
            "arguments": [],
            "keyword": "When ",
            "line": 24,
            "name": "the user inputs Mater value and DocumentID with status Current Bankrupt",
            "result": {
              "status": "passed",
              "duration": 6658000000
            }
          },
          {
            "arguments": [],
            "keyword": "And ",
            "line": 25,
            "name": "the user inputs Mater value and DocumentID with status Discharged Early",
            "result": {
              "status": "passed",
              "duration": 6873000000
            }
          },
          {
            "arguments": [],
            "keyword": "And ",
            "line": 26,
            "name": "the user inputs Mater value and DocumentID with status Conditionally Discharged",
            "result": {
              "status": "passed",
              "duration": 6910000000
            }
          },
          {
            "arguments": [],
            "keyword": "And ",
            "line": 27,
            "name": "the user inputs Mater value and DocumentID with status Current NAP",
            "result": {
              "status": "passed",
              "duration": 6894000000
            }
          },
          {
            "arguments": [],
            "keyword": "And ",
            "line": 28,
            "name": "the user inputs Mater value and DocumentID with status Completed",
            "result": {
              "status": "passed",
              "duration": 6911000000
            }
          },
          {
            "arguments": [],
            "keyword": "And ",
            "line": 29,
            "name": "the user inputs Mater value and DocumentID with status Current SIO",
            "result": {
              "status": "passed",
              "duration": 6919000000
            }
          },
          {
            "arguments": [],
            "keyword": "And ",
            "line": 30,
            "name": "the user inputs Mater value and DocumentID with status Currently in Liquidation",
            "result": {
              "status": "passed",
              "duration": 6922000000
            }
          },
          {
            "arguments": [],
            "keyword": "And ",
            "line": 31,
            "name": "the user inputs Mater value and DocumentID with status Automatically Discharged",
            "result": {
              "status": "passed",
              "duration": 6975000000
            }
          },
          {
            "arguments": [],
            "keyword": "And ",
            "line": 32,
            "name": "the user inputs Mater value and DocumentID with status Unspecified",
            "result": {
              "status": "passed",
              "duration": 6131000000
            }
          },
          {
            "arguments": [],
            "keyword": "And ",
            "line": 33,
            "name": "the user clicks on Order button to complete the Order",
            "result": {
              "status": "passed",
              "duration": 29590000000
            }
          },
          {
            "arguments": [],
            "keyword": "And ",
            "line": 34,
            "name": "the user sees the list of document is correct",
            "result": {
              "status": "passed",
              "duration": 273000000
            }
          },
          {
            "arguments": [],
            "keyword": "Then ",
            "line": 35,
            "name": "the user sees the orders with these status generated successfully",
            "result": {
              "status": "passed",
              "duration": 546000000
            }
          }
        ]
      }
    ]
  }
]